{
  "_id": "WvApparel0000064",
  "name": "Scrap Metal Armor",
  "type": "apparel",
  "data": {
    "name": "Scrap Metal Armor",
    "description": "",
    "notes": "User is Encumbered",
    "rules": {
      "sources": []
    },
    "rarity": "common",
    "value": 150,
    "weight": 20,
    "damageThreshold": 2,
    "quickSlots": 0,
    "modSlots": 5,
    "slot": "armor",
    "type": "heavyArmor"
  },
  "img": "icons/equipment/chest/breastplate-layered-steel-black.webp",
  "effects": [],
  "flags": {}
}
